MANIFEST.in
NEWS.txt
README.rst
bootstrap.py
setup.py
docs/conf.py
src/django_cpe.egg-info/PKG-INFO
src/django_cpe.egg-info/SOURCES.txt
src/django_cpe.egg-info/dependency_links.txt
src/django_cpe.egg-info/entry_points.txt
src/django_cpe.egg-info/not-zip-safe
src/django_cpe.egg-info/requires.txt
src/django_cpe.egg-info/top_level.txt
src/djangocpe/__init__.py
src/djangocpe/admin.py
src/djangocpe/api.py
src/djangocpe/cpedict23_handler.py
src/djangocpe/cpedict_parser.py
src/djangocpe/cpedict_parser_error.py
src/djangocpe/fields.py
src/djangocpe/models.py
src/djangocpe/serializers.py
src/djangocpe/urls.py
src/djangocpe/views.py
tests/test_cpedict_parser.py
tests/test_api/fixtures_api.py
tests/test_api/test_api_cpedata.py
tests/test_models/fixtures_models.py
tests/test_models/test_changedescription.py
tests/test_models/test_check.py
tests/test_models/test_cpedata.py
tests/test_models/test_cpeitem.py
tests/test_models/test_cpelist.py
tests/test_models/test_deprecatedby.py
tests/test_models/test_deprecation.py
tests/test_models/test_evidencereference.py
tests/test_models/test_generator.py
tests/test_models/test_note.py
tests/test_models/test_organization.py
tests/test_models/test_provenancerecord.py
tests/test_models/test_reference.py
tests/test_models/test_title.py
tests/test_parser/function_parsing.py
tests/test_parser/test_parser_changedescription.py
tests/test_parser/test_parser_check.py
tests/test_parser/test_parser_cpedata.py
tests/test_parser/test_parser_cpeitem.py
tests/test_parser/test_parser_deprecatedby.py
tests/test_parser/test_parser_deprecation.py
tests/test_parser/test_parser_evidencereference.py
tests/test_parser/test_parser_generator.py
tests/test_parser/test_parser_note.py
tests/test_parser/test_parser_provenancerecord.py
tests/test_parser/test_parser_reference.py
tests/test_parser/test_parser_submitter.py
tests/test_parser/test_parser_title.py